{
  "(multiple)": "(multiple)",
  "#_of_Gas_Records": "# de înregistrări de combustibil",
  "#_of_Notes": "# de note",
  "#_of_Odometer_Records": "# de înregistrări de odometru",
  "#_of_Plan_Records": "# de înregistrări de plan",
  "#_of_Reminders": "# de memento-uri",
  "#_of_Repair_Records": "# de înregistrări de reparații",
  "#_of_Service_Records": "# de înregistrări de servicii",
  "#_of_Supply_Records": "# de înregistrări de aprovizionare",
  "#_of_Tax_Records": "# de înregistrări fiscale",
  "#_of_Upgrade_Records": "# de înregistrări de upgrade",
  "\u002B30_Days": "\u002B30 Zile",
  "\u002B60_Days": "\u002B60 Zile",
  "\u002B90_Days": "\u002B90 Zile",
  "1_Month": "1 Lună",
  "1_Year": "1 An",
  "2_Years": "2 Ani",
  "3_Months": "3 Luni",
  "3_Years": "3 Ani",
  "5_Years": "5 Ani",
  "6_Months": "6 Luni",
  "A_token_has_been_generated_on_your_behalf,_please_complete_your_registration_for_LubeLogger_using_the_token": "Un token a fost generat în numele tău, te rugăm să finalizezi înregistrarea pentru LubeLogger folosind tokenul.",
  "A_token_has_been_generated_on_your_behalf,_please_reset_your_password_for_LubeLogger_using_the_token": "Un token a fost generat în numele tău, te rugăm să resetezi parola pentru LubeLogger folosind tokenul.",
  "A_token_has_been_generated_on_your_behalf,_please_update_your_account_for_LubeLogger_using_the_token": "Un token a fost generat în numele tău, te rugăm să îți actualizezi contul pentru LubeLogger folosind tokenul.",
  "About": "Despre",
  "Account_Username": "Nume utilizator cont",
  "Adaptive_Color_Mode": "Mod de culoare adaptiv",
  "Add_Gas_Record": "Adaugă înregistrare de combustibil",
  "Add_New_Field": "Adaugă câmp nou",
  "Add_New_Gas_Record": "Adaugă nouă înregistrare de combustibil",
  "Add_New_Note": "Adaugă notă nouă",
  "Add_New_Odometer_Record": "Adaugă nouă înregistrare de odometru",
  "Add_New_Plan_Record": "Adaugă nouă înregistrare de plan",
  "Add_New_Reminder": "Adaugă memento nou",
  "Add_New_Repair_Record": "Adaugă nouă înregistrare de reparație",
  "Add_New_Service_Record": "Adaugă nouă înregistrare de serviciu",
  "Add_New_Supply_Record": "Adaugă nouă înregistrare de aprovizionare",
  "Add_New_Tax_Record": "Adaugă nouă înregistrare fiscală",
  "Add_New_Upgrade_Record": "Adaugă nouă înregistrare de upgrade",
  "Add_New_Vehicle": "Adaugă vehicul nou",
  "Add_Note": "Adaugă notă",
  "Add_Odometer_Record": "Adaugă înregistrare de odometru",
  "Add_Plan_Record": "Adaugă înregistrare de plan",
  "Add_Reminder": "Adaugă memento",
  "Add_Repair_Record": "Adaugă înregistrare de reparație",
  "Add_Service_Record": "Adaugă înregistrare de serviciu",
  "Add_Supply_Record": "Adaugă înregistrare de aprovizionare",
  "Add_Tax_Record": "Adaugă înregistrare fiscală",
  "Add_Upgrade_Record": "Adaugă înregistrare de upgrade",
  "Additional_Widgets": "Widgeturi suplimentare",
  "Adjust_Odometer": "Ajustează odometrul",
  "Admin_Panel": "Panou de administrare",
  "Advanced_Filters": "Filtre avansate",
  "All_Time": "Tot timpul",
  "Amount_of_gas_refueled": "Cantitate de combustibil alimentată",
  "An_error_has_occurred,_please_try_again_later": "A apărut o eroare, te rugăm să încerci din nou mai târziu",
  "Appreciation": "Apreciere",
  "As_of_Today": "Începând de astăzi",
  "Attachments": "Atașamente",
  "Auto_Insert_Odometer_Records": "Inserare automată a înregistrărilor de odometru",
  "Auto_Notify(via_Email)": "Notificare automată (prin email)",
  "Auto_Refresh_Lapsed_Recurring_Reminders": "Reîmprospătare automată a memento-urilor recurente expirate",
  "Automatically_Format_Decimal_Inputs": "Formatare automată a intrărilor zecimale",
  "Available_Translations": "Traduceri disponibile",
  "Average_Fuel_Economy": "Economia medie de combustibil",
  "Back_to_Login": "Înapoi la autentificare",
  "Backups": "Backup-uri",
  "Calendar": "Calendar",
  "Cancel": "Anulează",
  "Choose_Additional_Supplies": "Alege aprovizionări suplimentare",
  "Choose_Supplies": "Alege aprovizionări",
  "Close": "Închide",
  "Collaborators": "Colaboratori",
  "Configure_Reminder_Urgency_Thresholds": "Configurează pragurile de urgență pentru memento-uri",
  "Consumption": "Consum",
  "Copy_Attachments": "Copiază atașamente",
  "Cost": "Cost",
  "Cost_of_gas_refueled": "Costul combustibilului alimentat",
  "Cost_of_tax_paid": "Costul impozitului plătit",
  "Cost_of_the_Plan": "Costul planului",
  "Cost_of_the_repair": "Costul reparației",
  "Cost_of_the_service": "Costul serviciului",
  "Cost_of_the_upgrade/mods": "Costul upgrade-ului/modificărilor",
  "Cost_Per_Day": "Cost pe zi",
  "Cost_Per_Hour": "Cost pe oră",
  "Cost_Per_Kilometer": "Cost pe kilometru",
  "Cost_Per_Mile": "Cost pe milă",
  "Create": "Creează",
  "Create_Odometer": "Creează odometru",
  "Critical": "Critic",
  "Current_Odometer": "Odometrul curent",
  "Current_Stage": "Etapa curentă",
  "Custom_Widgets_Editor": "Editor de widgeturi personalizate",
  "Dark_Mode": "Mod întunecat",
  "Dashboard": "Tabloul de bord",
  "Dashboard_Metrics": "Metrici tabloului de bord",
  "Database_Migration": "Migrarea bazei de date",
  "Date": "Dată",
  "Date_Created": "Data creată",
  "Date_purchased": "Data achiziției",
  "Date_recorded": "Data înregistrării",
  "Date_refueled": "Data alimentării",
  "Date_Refueled": "Data alimentării",
  "Date_repair_was_performed": "Data la care s-a efectuat reparația",
  "Date_service_was_performed": "Data la care s-a efectuat serviciul",
  "Date_tax_was_paid": "Data la care s-a plătit impozitul",
  "Date_upgrade/mods_was_installed": "Data la care s-a instalat upgrade-ul/modificările",
  "day": "zi",
  "Days": "Zile",
  "Default_Email_for_Reminder": "Email implicit pentru memento",
  "Default_Reminder_Email": "Email implicit pentru memento",
  "Default_Tab": "Tab implicit",
  "Default_to_Fuel_Unit_Cost": "Setează costul unității de combustibil ca implicit",
  "Delete": "Șterge",
  "Delete_Vehicle": "Șterge vehiculul",
  "Delta": "Delta",
  "Depreciation": "Amortizare",
  "Describe_the_Plan": "Descrie planul",
  "Description": "Descriere",
  "Description_of_item(s)_repaired(i.e._Alternator)": "Descrierea elementelor reparate (de exemplu, alternator)",
  "Description_of_item(s)_serviced(i.e._Oil_Change)": "Descrierea elementelor întreținute (de exemplu, schimb de ulei)",
  "Description_of_item(s)_upgraded/modded": "Descrierea elementelor actualizate/modificate",
  "Description_of_tax_paid(i.e._Registration)": "Descrierea impozitului plătit (de exemplu, înregistrare)",
  "Description_of_the_note": "Descrierea notei",
  "Description_of_the_Part/Supplies": "Descrierea piesei/aprovizionărilor",
  "Deselect_All": "Deselează tot",
  "Diesel": "Motorină",
  "Disable_Registration": "Dezactivează înregistrarea",
  "Display_Saved_Notes_in_Markdown": "Afișează notele salvate în Markdown",
  "Distance": "Distanță",
  "Distance_Traveled_by_Month": "Distanța parcursă pe lună",
  "Documents_Pending_Upload": "Documente în așteptare pentru încărcare",
  "Doing": "Se face",
  "Done": "Finalizat",
  "Download_All_Translations": "Descarcă toate traducerile",
  "Download_Sample": "Descarcă exemplu",
  "Due": "Scadent",
  "Duplicate": "Duplicat",
  "Duplicate_To_Vehicle": "Duplicat pentru vehicul",
  "Edit": "Editează",
  "Edit_Gas_Record": "Editează înregistrarea de combustibil",
  "Edit_Multiple": "Editează multiple",
  "Edit_Multiple_Gas_Records": "Editează multiple înregistrări de combustibil",
  "Edit_Multiple_Odometer_Records": "Editează multiple înregistrări de odometru",
  "Edit_Multiple_Records": "Editează multiple înregistrări",
  "Edit_Note": "Editează notă",
  "Edit_Odometer_Record": "Editează înregistrarea de odometru",
  "Edit_Plan_Record": "Editează înregistrarea de plan",
  "Edit_Plan_Record_Template": "Editează șablonul înregistrării de plan",
  "Edit_Reminder": "Editează memento",
  "Edit_Repair_Record": "Editează înregistrarea de reparație",
  "Edit_Service_Record": "Editează înregistrarea de serviciu",
  "Edit_Supply_Record": "Editează înregistrarea de aprovizionare",
  "Edit_Tax_Record": "Editează înregistrarea fiscală",
  "Edit_Upgrade_Record": "Editează înregistrarea de upgrade",
  "Edit_Vehicle": "Editează vehiculul",
  "Electric": "Electric",
  "Electric_Vehicle": "Vehicul electric",
  "Email": "Email",
  "Email_Address": "Adresă de email",
  "Enable_Authentication": "Activează autentificarea",
  "Enable_CSV_Imports": "Activează importurile CSV",
  "Enable_OIDC_for_Root_User": "Activează OIDC pentru utilizatorul root",
  "Enabling_this_may_cause_performance_issues": "Activarea acestuia poate cauza probleme de performanță",
  "End_Date": "Data de încheiere",
  "Exclude_Records_with_these_Tags": "Excluzi înregistrările cu aceste etichete",
  "Expenses_and_Distance_Traveled_by_Month": "Cheltuieli și distanță parcursă pe lună",
  "Expenses_by_Month": "Cheltuieli pe lună",
  "Expenses_by_Type": "Cheltuieli pe tip",
  "Experimental_Feature_-_Do_not_exit_or_minimize_this_app_when_recording._Verify_all_starting_and_ending_odometers._Accuracy_subject_to_hardware_limitations.": "Funcție experimentală - Nu ieși sau minimizează această aplicație când înregistrezi. Verifică toate odometrele de început și de sfârșit. Precizia este supusă limitărilor hardware.",
  "Export_Attachments": "Exportă atașamente",
  "Export_From_Postgres": "Exportă din Postgres",
  "Export_to_CSV": "Exportă în CSV",
  "Export_Translation": "Exportă traducerea",
  "Extra_Fields": "Câmpuri suplimentare",
  "Failure_to_format_the_data_correctly_can_cause_data_corruption._Please_make_sure_you_make_a_copy_of_the_local_database_before_proceeding.": "Eșecul de a formata datele corect poate cauza coruperea datelor. Te rugăm să te asiguri că faci o copie a bazei de date locale înainte de a continua.",
  "Filter_by_Date_Range": "Filtrează după interval de date",
  "Filter_by_Tags": "Filtrează după etichete",
  "Forgot_Password": "Ai uitat parola",
  "From": "De la",
  "From_Postgres": "Din Postgres",
  "Fuel": "Combustibil",
  "Fuel_Consumption": "Consum de combustibil",
  "Fuel_Economy": "Economia de combustibil",
  "Fuel_Mileage_by_Month": "Kilometrajul combustibilului pe lună",
  "Fuel_Type": "Tip de combustibil",
  "Future_Date": "Dată viitoare",
  "Future_Odometer_Reading": "Citire viitoare a odometrului",
  "gallons": "galoane",
  "Garage": "Garaj",
  "Gasoline": "Benzină",
  "Generate": "Generează",
  "Generate_User_Token": "Generează token de utilizator",
  "Get_Translations": "Obține traduceri",
  "Hide_Sold_Vehicles": "Ascunde vehiculele vândute",
  "hours": "ore",
  "I_Have_a_Token": "Am un token",
  "Identifier": "Identificator",
  "Import": "Importă",
  "Import_Data_from_CSV": "Importă date din CSV",
  "Import_To_Postgres": "Importă în Postgres",
  "Import_via_CSV": "Importă prin CSV",
  "In_order_for_this_utility_to_function_properly,_your_CSV_file_MUST_be_formatted_exactly_like_the_provided_sample._Dates_must_be_supplied_in_a_string._Numbers_must_be_supplied_as_numbers_without_currency_formatting.": "Pentru ca această utilitate să funcționeze corect, fișierul tău CSV TREBUIE să fie formatat exact ca exemplul furnizat. Datele trebuie furnizate sub formă de șir. Numerele trebuie furnizate ca numere fără formatare monetară.",
  "In_Stock": "În stoc",
  "Incremental_Search": "Căutare incrementală",
  "Initial_Odometer": "Odometrul inițial",
  "Initial_Odometer_reading": "Citirea inițială a odometrului",
  "Input_Gas_Consumption_in_Liters,_it_will_be_converted_to_UK_Gals_for_MPG_Calculation": "Introdu consumul de combustibil în litri, va fi convertit în galoane UK pentru calculul MPG",
  "Instructions": "Instrucțiuni",
  "Is_Admin": "Este administrator",
  "Is_Filled_To_Full": "Este umplut complet",
  "Is_Recurring": "Este recurent",
  "Issued_To": "Emis către",
  "kilometers": "kilometri",
  "Language": "Limbă",
  "Last_Modified": "Ultima modificare",
  "Last_Odometer": "Ultimul odometru",
  "Last_Reported_Odometer_Reading": "Ultima citire raportată a odometrului",
  "License_Plate": "Număr de înmatriculare",
  "liters": "litri",
  "Login": "Autentificare",
  "Login_via": "Autentificare prin",
  "Logout": "Deconectare",
  "Low": "Scăzut",
  "Make": "Marca",
  "Manage_Extra_Fields": "Gestionează câmpuri suplimentare",
  "Manage_Languages": "Gestionează limbile",
  "Manage_Tokens": "Gestionează tokenurile",
  "Manage_Vehicle": "Gestionează vehiculul",
  "Mark_as_Done": "Marchează ca finalizat",
  "Max_File_Size:_28.6MB": "Dimensiunea maximă a fișierului: 28.6MB",
  "Max_Fuel_Economy": "Economia maximă de combustibil",
  "Metric": "Metric",
  "Metrics": "Metrici",
  "miles": "mile",
  "Min_Fuel_Economy": "Economia minimă de combustibil",
  "Missed_Fuel_Up(Skip_MPG_Calculation)": "Combustibil ratat (sari peste calculul MPG)",
  "Missing_Supplies,_Please_Delete_This_Template_and_Recreate_It.": "Aprovizionări lipsă, te rugăm să ștergi acest șablon și să-l recreezi.",
  "Model": "Model",
  "Month": "Lună",
  "Move_To": "Mută la",
  "Multiple": "Multiple",
  "Name": "Nume",
  "New_Password": "Parolă nouă",
  "No_Data_Found": "Nu s-au găsit date",
  "No_data_found_or_all_records_have_zero_sums,_insert_records_with_non-zero_sums_to_see_visualizations_here.": "Nu s-au găsit date sau toate înregistrările au sume zero, introdu înregistrări cu sume diferite de zero pentru a vedea vizualizările aici.",
  "No_data_found,_create_reminders_to_see_visualizations_here.": "Nu s-au găsit date, creează memento-uri pentru a vedea vizualizările aici.",
  "No_data_found,_insert/select_some_data_to_see_visualizations_here.": "Nu s-au găsit date, introdu/selectează unele date pentru a vedea vizualizările aici.",
  "No_records_available_to_display": "Nu sunt disponibile înregistrări de afișat",
  "No_Recurring_Reminders_Found": "Nu s-au găsit memento-uri recurente",
  "No_supplies_with_quantities_greater_than_0_is_found.": "Nu s-au găsit aprovizionări cu cantități mai mari de 0.",
  "No_supply_requisitions_in_history": "Nu există cereri de aprovizionare în istoric",
  "No_templates_are_found.": "Nu s-au găsit șabloane.",
  "No_Vehicles_Available": "Nu sunt vehicule disponibile",
  "Normal": "Normal",
  "Not_Urgent": "Nu este urgent",
  "Note": "Notă",
  "Note_that_it_is_recommended_that_the_Postgres_DB_is_empty_when_importing_from_LiteDB_to_prevent_primary_key_errors": "Se recomandă ca baza de date Postgres să fie goală atunci când se importă din LiteDB pentru a preveni erorile de cheie primară.",
  "Notes": "Note",
  "Notes(optional)": "Note (opțional)",
  "Notes(use_---_to_clear_all_existing_notes)": "Note (folosește --- pentru a șterge toate notele existente)",
  "Notify": "Notifică",
  "Odometer": "Odometrul",
  "Odometer_Adjustments": "Ajustări ale odometrului",
  "Odometer_Difference": "Diferența de odometru",
  "Odometer_Multiplier": "Multiplicator de odometru",
  "Odometer_Optional": "Odometrul opțional",
  "Odometer_reading": "Citirea odometrului",
  "Odometer_Reading": "Citirea odometrului",
  "Odometer_reading_when_refueled": "Citirea odometrului când a fost alimentat",
  "Odometer_reading_when_repaired": "Citirea odometrului când a fost reparat",
  "Odometer_reading_when_serviced": "Citirea odometrului când a fost întreținut",
  "Odometer_reading_when_upgraded/modded": "Citirea odometrului când a fost actualizat/modificat",
  "Only_Include_Records_with_these_Tags": "Include doar înregistrările cu aceste etichete",
  "Only_when_Adding_Service/Repair/Upgrade/Fuel_Record_or_Completing_a_Plan": "Numai când adaugi înregistrări de serviciu/reparație/upgrade/combustibil sau finalizezi un plan",
  "Order_Supplies": "Comandă aprovizionări",
  "Other": "Altele",
  "Part_#": "Partea #",
  "Part_#/Model_#/SKU_#": "Partea #/Model #/SKU #",
  "Part_Number": "Numărul piesei",
  "Part_Supplier": "Furnizorul piesei",
  "Password": "Parolă",
  "Past_Due": "Scadent",
  "Pin": "Fixează",
  "Pinned": "Fixat",
  "Plan": "Plan",
  "Planned": "Planificat",
  "Planner": "Planificator",
  "Plans": "Planuri",
  "Print": "Imprimă",
  "Priority": "Prioritate",
  "Profile": "Profil",
  "Purchase/Sold_Information(optional)": "Informații de achiziție/vânzare (opțional)",
  "Purchased_Date": "Data achiziției",
  "Purchased_Date(optional)": "Data achiziției (opțional)",
  "Purchased_Price": "Preț achiziționat",
  "Purchased_Price(optional)": "Preț achiziționat (opțional)",
  "Quantity": "Cantitate",
  "Recalculate_Distance": "Recalculează distanța",
  "Register": "Înregistrează",
  "Remember_Me": "Ține-mă minte",
  "Remind_me_on": "Amintește-mi pe",
  "Reminder": "Memento",
  "Reminder_Description": "Descrierea memento-ului",
  "Reminders": "Memento-uri",
  "Reminders_by_Category": "Memento-uri pe categorii",
  "Reminders_by_Urgency": "Memento-uri pe urgență",
  "Reorder_Tabs": "Reordonează tab-urile",
  "Repair": "Reparație",
  "Repairs": "Reparații",
  "Replace_$0.00_Costs_with_---": "Înlocuiește costurile de $0.00 cu ---",
  "Replace_picture(optional)": "Înlocuiește imaginea (opțional)",
  "Request": "Cerere",
  "Required": "Necesar",
  "Reset_Password": "Resetează parola",
  "Reset_Tab_Order": "Resetează ordinea tab-urilor",
  "Restore": "Restaurare",
  "Save": "Salvează",
  "Save_as_Template": "Salvează ca șablon",
  "Save_Tab_Order": "Salvează ordinea tab-urilor",
  "Save_Translation": "Salvează traducerea",
  "Save_Vehicle": "Salvează vehiculul",
  "Search": "Caută",
  "Search_by_Keyword(Case_Sensitive)": "Caută după cuvânt cheie (sensibil la majuscule)",
  "Select": "Selectează",
  "Select_All": "Selectează tot",
  "Select_Columns": "Selectează coloanele",
  "Select_Mode": "Mod de selecție",
  "Select_Reminder": "Selectează memento",
  "Select_Supplies": "Selectează aprovizionări",
  "Select_Template": "Selectează șablon",
  "Send_Token": "Trimite token",
  "Server-wide_Settings": "Setări la nivel de server",
  "Service": "Serviciu",
  "Service_Record": "Înregistrare de serviciu",
  "Service_Records": "Înregistrări de servicii",
  "Settings": "Setări",
  "Shop_Supplies": "Aprovizionări magazin",
  "Show_Extra_Field_Columns": "Afișează coloanele câmpurilor suplimentare",
  "SOLD": "VÂNDUT",
  "Sold_Date": "Data vânzării",
  "Sold_Date(optional)": "Data vânzării (opțional)",
  "Sold_Price": "Preț vândut",
  "Sold_Price(optional)": "Preț vândut (opțional)",
  "Sort_lists_in_Descending_Order(Newest_to_Oldest)": "Sortează listele în ordine descrescătoare (de la cele mai recente la cele mai vechi)",
  "Sponsors": "Sponsorii",
  "Start_Date": "Data de început",
  "Start_Recording": "Începe înregistrarea",
  "Statistics": "Statistici",
  "Stop_Recording": "Oprește înregistrarea",
  "Supplier": "Furnizor",
  "Supplier/Vendor": "Furnizor/Vânzător",
  "Supplies": "Aprovizionări",
  "Supplies_are_requisitioned_immediately_after_the_record_is_saved.": "Aprovizionările sunt cerute imediat după ce înregistrarea este salvată.",
  "Supply_Requisition_History": "Istoricul cererilor de aprovizionare",
  "Tags(optional)": "Etichete (opțional)",
  "Tags(use_---_to_clear_all_existing_tags)": "Etichete (folosește --- pentru a șterge toate etichetele existente)",
  "Tax": "Impozit",
  "Taxes": "Impozite",
  "Testing": "Testare",
  "This_Will_Also_Change_Units_to_Miles_and_Gallons": "Aceasta va schimba de asemenea unitățile în mile și galoane",
  "Time": "Timp",
  "To": "Către",
  "To_Postgres": "Către Postgres",
  "Toggle_Pin": "Comută fixarea",
  "Token": "Token",
  "Tokens": "Tokenuri",
  "Total": "Total",
  "Total_Cost": "Cost total",
  "Total_Cost_/_Total_Distance_Driven": "Cost total / Distanță totală parcursă",
  "Total_Distance": "Distanță totală",
  "Total_Fuel_Consumed": "Combustibil total consumat",
  "Total_Spent_on_Fuel": "Total cheltuit pe combustibil",
  "Total_Spent(excl._fuel)": "Total cheltuit (excl. combustibil)",
  "Translation_Editor": "Editor de traduceri",
  "Type": "Tip",
  "Unit": "Unitate",
  "Unit_Cost": "Cost pe unitate",
  "Unpin": "Dezfixează",
  "Unsaved_Changes": "Modificări nesalvate",
  "Upcoming_Reminder": "Memento viitor",
  "Update": "Actualizează",
  "Update_Profile": "Actualizează profilul",
  "Upgrade": "Upgrade",
  "Upgrades": "Upgrade-uri",
  "Upload": "Încărcare",
  "Upload_a_picture(optional)": "Încărcați o imagine (opțional)",
  "Upload_CSV_File": "Încărcați fișier CSV",
  "Upload_documents(optional)": "Încărcați documente (opțional)",
  "Upload_more_documents": "Încărcați mai multe documente",
  "Uploaded_Documents": "Documente încărcate",
  "Urgency": "Urgență",
  "Urgent": "Urgent",
  "Urgent(Days)": "Urgent (Zile)",
  "Urgent(Distance)": "Urgent (Distanță)",
  "Use": "Folosește",
  "Use_Custom_Thresholds": "Folosește praguri personalizate",
  "Use_Engine_Hours": "Folosește orele motorului",
  "Use_Imperial_Calculation_for_Fuel_Economy_Calculations(MPG)": "Folosește calcul imperial pentru calculele economiei de combustibil (MPG)",
  "Use_this_tool_to_migrate_data_between_LiteDB_and_Postgres": "Folosește acest instrument pentru a migra date între LiteDB și Postgres",
  "Use_Three_Decimals_For_Fuel_Consumption": "Folosește trei zecimale pentru consumul de combustibil",
  "Use_Three_Decimals_For_Fuel_Cost": "Folosește trei zecimale pentru costul combustibilului",
  "Use_UK_MPG_Calculation": "Folosește calculul MPG din Marea Britanie",
  "Username": "Nume utilizator",
  "Users": "Utilizatori",
  "Uses_the_Default_Reminder_Email_for_OIDC_Auth": "Folosește emailul implicit pentru memento pentru autentificarea OIDC",
  "Vehicle": "Vehicul",
  "Vehicle_Cost_Breakdown": "Detalierea costurilor vehiculului",
  "Vehicle_Maintenance_Report": "Raport de întreținere a vehiculului",
  "Vehicle_Monthly_Cost_Breakdown": "Detalierea costurilor lunare ale vehiculului",
  "Vehicle_Reminders_From_LubeLogger": "Memento-uri pentru vehicul de la LubeLogger",
  "Version": "Versiune",
  "Very_Urgent": "Foarte urgent",
  "Very_Urgent(Days)": "Foarte urgent (Zile)",
  "Very_Urgent(Distance)": "Foarte urgent (Distanță)",
  "View_Reminder": "Vezi memento",
  "View_Templates": "Vezi șabloane",
  "Visible_Columns": "Coloane vizibile",
  "Visible_Tabs": "Tab-uri vizibile",
  "Whichever_comes_first": "Oricare apare prima",
  "Year": "An",
  "Year(must_be_after_1900)": "An (trebuie să fie după 1900)",
  "Your_Password_Reset_Token_for_LubeLogger": "Tokenul tău de resetare a parolei pentru LubeLogger",
  "Your_Registration_Token_for_LubeLogger": "Tokenul tău de înregistrare pentru LubeLogger",
  "Your_User_Account_Update_Token_for_LubeLogger": "Tokenul tău de actualizare a contului de utilizator pentru LubeLogger"
}
